r3dir/__init__.py
r3dir/_cli.py
r3dir/encoder.py
r3dir/exceptions.py
r3dir/hackvertor/encoder.js
r3dir-0.2.3.2.dist-info/LICENSE
r3dir-0.2.3.2.dist-info/METADATA
r3dir-0.2.3.2.dist-info/WHEEL
r3dir-0.2.3.2.dist-info/entry_points.txt
r3dir-0.2.3.2.dist-info/top_level.txt
r3dir-0.2.3.2.dist-info/RECORD
