Metadata-Version: 2.1
Name: r3dir
Version: 0.2.3.2
Summary: r3dir encoder/decoder package with CLI tool
Author: Horlad
Project-URL: Homepage, https://github.com/Horlad/r3dir
Project-URL: Bug Tracker, https://github.com/Horlad/r3dir/issues
Classifier: Programming Language :: Python :: 3
Classifier: License :: OSI Approved :: Apache Software License
Classifier: Operating System :: OS Independent
Requires-Python: >=3.10
License-File: LICENSE
Requires-Dist: unishox2-py3
Requires-Dist: pyperclip
